DAY_006/CLA.v
module cla(input [3:0] a, b , input cin , output [3:0] sum , output carry);

wire [3:0] cout;





assign cout[0] = (a[0]&b[0]) | ((a[0] | b[0] ) & cin);

assign cout[1] = (a[1] & b[1]) | ((a[1] | b[1]) & (a[0] & b[0])) | ((a[1] | b[1] ) & ((a[0] | b[0] ) & cin));

assign cout[2] = (a[2] & b[2]) | ((b[2] | b[2]) & ((a[1] & b[1]))) | ((b[2] | b[2])  &  ((a[1] | b[1]) & (a[0] & b[0]))) | ((b[2] | b[2])  & ((a[1] | b[1] ) & ((a[0] | b[0] ) & cin)));

assign cout[3] = (a[3] & b[3]) | ((a[3] | b[3]) & (a[2] & b[2])) | ((a[3] | b[3]) & (b[2] | b[2]) & ((a[1] & b[1]))) | ((a[3] | b[3]) & ((b[2] | b[2])  &  ((a[1] | b[1]) & (a[0] & b[0])))) | (((a[3] | b[3])) &  ((b[2] | b[2])  & ((a[1] | b[1] ) & ((a[0] | b[0] ) & cin))));


assign sum = a ^ b ^ {cout[2], cout[1], cout[0], cin};
assign carry = cout[3];
endmodule

DAY_006/CLA_tb.v
module tb_cla;
    // Testbench signals
    reg [3:0] a, b;
    reg cin;
    wire [3:0] sum;
    wire carry;
	
    // Instantiate the CLA module
    cla uut (
        .a(a),
        .b(b),
        .cin(cin),
        .sum(sum),
        .carry(carry)
    );

/*    // Test vectors and simulation
    initial begin
        // Display the results in a readable format
        $monitor("Time = %0t | a = %b | b = %b | cin = %b | sum = %b | carry = %b", 
                 $time, a, b, cin, sum, carry);

        // Test case 1
        a = 4'b0000; b = 4'b0000; cin = 1'b0;
        #10;

        // Test case 2
        a = 4'b0101; b = 4'b0011; cin = 1'b0;
        #10;

        // Test case 3
        a = 4'b1111; b = 4'b0001; cin = 1'b1;
        #10;

        // Test case 4
        a = 4'b1010; b = 4'b0101; cin = 1'b1;
        #10;

        // Test case 5
        a = 4'b1100; b = 4'b1100; cin = 1'b0;
        #10;

        // Test case 6
        a = 4'b0110; b = 4'b1001; cin = 1'b1;
        #10;

        // End the simulation
        $finish;
	end
*/

integer i;

    initial begin


      for (i =  0; i <=20 ; i = i+1)
      begin
	      #10;
	      a = $urandom_range(0,10);
	      b = $urandom_range(0,10);
	      cin = $urandom_range(0,1);
	      
      end

    
    end


     initial begin
        // Display the results in a readable format
        $monitor("Time = %0t | a = %b | b = %b | cin = %b | sum = %b | carry = %b", $time, a, b, cin, sum, carry);
     end   

    initial begin
     $dumpfile("cla.vcd");
     $dumpvars(0,tb_cla);
    end
 
endmodule

DAY_006/cla.vcd
$date
	Tue Jul  8 09:33:37 2025
$end
$version
	Icarus Verilog
$end
$timescale
	1s
$end
$scope module tb_cla $end
$var wire 4 ! sum [3:0] $end
$var wire 1 " carry $end
$var reg 4 # a [3:0] $end
$var reg 4 $ b [3:0] $end
$var reg 1 % cin $end
$var integer 32 & i [31:0] $end
$scope module uut $end
$var wire 4 ' a [3:0] $end
$var wire 4 ( b [3:0] $end
$var wire 1 % cin $end
$var wire 4 ) sum [3:0] $end
$var wire 4 * cout [3:0] $end
$var wire 1 " carry $end
$upscope $end
$upscope $end
$enddefinitions $end
$comment Show the parameter values. $end
$dumpall
$end
#0
$dumpvars
bx *
bx )
bx (
bx '
b0 &
x%
bx $
bx #
x"
bx !
$end
#10
0"
b10 *
b0 !
b0 )
b1 &
0%
b10 $
b10 (
b110 #
b110 '
#20
b111 *
b1000 !
b1000 )
b10 &
1%
b101 $
b101 (
b10 #
b10 '
#30
b0 *
b11 !
b11 )
b11 &
b0 $
b0 (
#40
b1 *
b1110 !
b1110 )
b100 &
b1000 $
b1000 (
b101 #
b101 '
#50
1"
b1000 *
b11 !
b11 )
b101 &
b1010 #
b1010 '
#60
0"
b100 *
b1000 !
b1000 )
b110 &
0%
b100 $
b100 (
b100 #
b100 '
#70
b10 *
b1100 !
b1100 )
b111 &
b10 $
b10 (
b1010 #
b1010 '
#80
1"
b1000 *
b10 !
b10 )
b1000 &
b1010 $
b1010 (
b1000 #
b1000 '
#90
0"
b100 *
b1001 !
b1001 )
b1001 &
1%
b100 $
b100 (
b100 #
b100 '
#100
b0 *
b100 !
b100 )
b1010 &
0%
b0 $
b0 (
#110
b111 !
b111 )
b1011 &
b101 $
b101 (
b10 #
b10 '
#120
b1111 !
b1111 )
b1100 &
b1001 $
b1001 (
b110 #
b110 '
#130
b11 !
b11 )
b1101 &
b0 $
b0 (
b11 #
b11 '
#140
b111 *
b1000 !
b1000 )
b1110 &
b111 $
b111 (
b1 #
b1 '
#150
b11 *
b100 !
b100 )
b1111 &
1%
b11 $
b11 (
b0 #
b0 '
#160
b100 *
b1011 !
b1011 )
b10000 &
b110 $
b110 (
b100 #
b100 '
#170
b1 *
b110 !
b110 )
b10001 &
b1 $
b1 (
#180
b0 *
b1110 !
b1110 )
b10010 &
0%
b110 $
b110 (
b1000 #
b1000 '
#190
b1011 !
b1011 )
b10011 &
1%
b10 $
b10 (
#200
1"
b1001 *
b11 !
b11 )
b10100 &
b1001 $
b1001 (
b1001 #
b1001 '
#210
0"
b100 *
b1010 !
b1010 )
b10101 &
0%
b110 $
b110 (
b100 #
b100 '
