DAY_008/demux1x4.v
module demux(
    input in,
    input [1:0] sel,
    output [3:0] x
);

assign x[0] = (sel == 2'b00) ? in : 1'b0;
assign x[1] = (sel == 2'b01) ? in : 1'b0;
assign x[2] = (sel == 2'b10) ? in : 1'b0;
assign x[3] = (sel == 2'b11) ? in : 1'b0;

endmodule

/*
module demux_1to8_case (
    input in,
    input [2:0] sel,
    output reg [7:0] x
);
    always @(*) begin
        case (sel)
            3'b000: x[0] = in;
            3'b001: x[1] = in;
            3'b010: x[2] = in;
            3'b011: x[3] = in;
            3'b100: x[4] = in;
            3'b101: x[5] = in;
            3'b110: x[6] = in;
            3'b111: x[7] = in;
	    default :  x = 8'b00000000; // Default: all outputs 0
        endcase
    end
endmodule
*/

/*

module demux_1to8_if (
    input in,
    input [2:0] sel,
    output reg [7:0] x
);
    always @(*) begin
        

        if (sel == 3'b000) x[0] = in;
        else if (sel == 3'b001) x[1] = in;
        else if (sel == 3'b010) x[2] = in;
        else if (sel == 3'b011) x[3] = in;
        else if (sel == 3'b100) x[4] = in;
        else if (sel == 3'b101) x[5] = in;
        else if (sel == 3'b110) x[6] = in;
        else if (sel == 3'b111) x[7] = in;'
	else x = 8'b00000000; // Default: all outputs 0
    end
endmodule
*/

DAY_008/demum_tb.v
module tb;
reg in;
reg [1:0] sel;
wire [3:0]x;

demux dut(in ,sel,x);


initial begin
  repeat(10) begin
   
      in = $urandom_range(0,1);
      sel = $urandom_range(0,5);
      #10;
   end
   
end
initial begin
 $monitor("in = %0d , sel = %0d , x = %0d ", in ,sel ,x);
 $dumpfile("demux.vcd");
 $dumpvars(0,tb);
end
endmodule

DAY_008/demux.vcd
$date
	Sun Jul 13 12:12:11 2025
$end
$version
	Icarus Verilog
$end
$timescale
	1s
$end
$scope module tb $end
$var wire 4 ! x [3:0] $end
$var reg 1 " in $end
$var reg 2 # sel [1:0] $end
$scope module dut $end
$var wire 1 " in $end
$var wire 2 $ sel [1:0] $end
$var wire 4 % x [3:0] $end
$upscope $end
$upscope $end
$enddefinitions $end
$comment Show the parameter values. $end
$dumpall
$end
#0
$dumpvars
b10 %
b1 $
b1 #
1"
b10 !
$end
#10
b0 !
b0 %
0"
#20
b1 !
b1 %
b0 #
b0 $
1"
#30
b0 !
b0 %
0"
#40
b1000 !
b1000 %
b11 #
b11 $
1"
#60
b1 !
b1 %
b0 #
b0 $
#70
b100 !
b100 %
b10 #
b10 $
#80
b0 !
b0 %
b1 #
b1 $
0"
#90
b10 !
b10 %
1"
