DAY_014/b2g_converter.v
module b2g(binary,gray);
input [3:0] binary;
output [3:0]gray;

assign gray[3] = binary[3];   //// MSB remains the same
assign gray[2] = binary[3] ^ binary[2]; // G2 = B3 XOR B2
assign gray[1] = binary[2] ^ binary[1]; // G1 = B3 XOR B1
assign gray[0] = binary[1] ^ binary[0];	// G0 = B3 XOR B0
endmodule

DAY_014/b2g_tb.v
module tb();
reg [3:0] binary;
wire [3:0] gray;

b2g dut(binary,gray);


integer i;
initial begin
 for(i=0 ; i<15 ; i=i+1)
  begin
    binary = i;
    #10;
  end
end

initial begin
 $monitor("Time = %0t , binary = %0d , gray = %0d ",$time,binary,gray);
 $dumpfile("b2g.vcd");
 $dumpvars(0,tb);
end
endmodule

DAY_014/b2g.vcd
$date
	Sat Jul 19 09:54:30 2025
$end
$version
	Icarus Verilog
$end
$timescale
	1s
$end
$scope module tb $end
$var wire 4 ! gray [3:0] $end
$var reg 4 " binary [3:0] $end
$var integer 32 # i [31:0] $end
$scope module dut $end
$var wire 4 $ binary [3:0] $end
$var wire 4 % gray [3:0] $end
$upscope $end
$upscope $end
$enddefinitions $end
$comment Show the parameter values. $end
$dumpall
$end
#0
$dumpvars
b0 %
b0 $
b0 #
b0 "
b0 !
$end
#10
b1 !
b1 %
b1 "
b1 $
b1 #
#20
b11 !
b11 %
b10 "
b10 $
b10 #
#30
b10 !
b10 %
b11 "
b11 $
b11 #
#40
b110 !
b110 %
b100 "
b100 $
b100 #
#50
b111 !
b111 %
b101 "
b101 $
b101 #
#60
b101 !
b101 %
b110 "
b110 $
b110 #
#70
b100 !
b100 %
b111 "
b111 $
b111 #
#80
b1100 !
b1100 %
b1000 "
b1000 $
b1000 #
#90
b1101 !
b1101 %
b1001 "
b1001 $
b1001 #
#100
b1111 !
b1111 %
b1010 "
b1010 $
b1010 #
#110
b1110 !
b1110 %
b1011 "
b1011 $
b1011 #
#120
b1010 !
b1010 %
b1100 "
b1100 $
b1100 #
#130
b1011 !
b1011 %
b1101 "
b1101 $
b1101 #
#140
b1001 !
b1001 %
b1110 "
b1110 $
b1110 #
#150
b1111 #
