DAY_004/FA.v
module full_adder(input a,b,cin,output sum,carry);
wire w1,w2,w3,w4,w5;

xor g1 (w1,a,b);
and g2 (w2,a,b);

xor g3 (w3,w1,cin);
and g4 (w4,w1,cin);

or g5 (w5,w2,w4);


assign sum = w3;
assign carry = w5;
endmodule


/*
module full_adder(input a , b , cin , output sum, carry);
assign sum = a ^ b ^ cin;
assign carry = a&b | a&cin | b$cin ;
endmodule
*/

/*
module full_adder(input a , b , cin , output sum, carry);
assign {carry , sum } = a+b+cin;
endmodule
*/

DAY_004/FA_tb.v
module tb();
reg a,b,cin;
wire sum,carry;

full_adder dut(a,b,cin,sum,carry);

initial begin
  a = 0; b = 0; cin = 0 ; #10;
  a = 0; b = 0; cin = 1 ; #10;
  a = 0; b = 1; cin = 0 ; #10;
  a = 0; b = 1; cin = 1 ; #10;
  a = 1; b = 0; cin = 0 ; #10;
  a = 1; b = 0; cin = 1 ; #10;
  a = 1; b = 1; cin = 0 ; #10;
  a = 1; b = 1; cin = 1 ; #10;
end


initial begin
 $monitor("a = %0d , b = %0d , cin = %0d , sum = %0d , carry = %0d ", a,b,cin,sum,carry);
 $dumpfile("full_adder.vcd");
 $dumpvars(0,tb);
end

endmodule

DAY_004/full_adder.vcd
$date
	Sun Jul  6 18:58:44 2025
$end
$version
	Icarus Verilog
$end
$timescale
	1s
$end
$scope module tb $end
$var wire 1 ! sum $end
$var wire 1 " carry $end
$var reg 1 # a $end
$var reg 1 $ b $end
$var reg 1 % cin $end
$scope module dut $end
$var wire 1 # a $end
$var wire 1 $ b $end
$var wire 1 " carry $end
$var wire 1 % cin $end
$var wire 1 ! sum $end
$var wire 1 & w1 $end
$var wire 1 ' w2 $end
$var wire 1 ( w3 $end
$var wire 1 ) w4 $end
$var wire 1 * w5 $end
$upscope $end
$upscope $end
$enddefinitions $end
$comment Show the parameter values. $end
$dumpall
$end
#0
$dumpvars
0*
0)
0(
0'
0&
0%
0$
0#
0"
0!
$end
#10
1!
1(
1%
#20
1&
0%
1$
#30
1"
1*
0!
0(
1)
1%
#40
0"
0*
1!
1(
0)
0%
0$
1#
#50
1"
1*
0!
0(
1)
1%
#60
0)
0&
1'
0%
1$
#70
1!
1(
1%
