DAY_005/RCA.v

module Full_adder(input in1,in2,cin,output s,c);
assign {c,s} = in1+in2+cin;
endmodule


module ripple_carry_adder(input [3:0]a,b, input cin , output [3:0]sum ,output carry );

wire [3:0]cout;

Full_adder g1(a[0],b[0],cin,sum[0],cout[0]);
Full_adder g2(a[1],b[1],cout[0],sum[1],cout[1]);
Full_adder g3(a[2],b[2],cout[1],sum[2],cout[2]);
Full_adder g4(a[3],b[3],cout[2],sum[3],cout[3]);

assign carry = cout[3];

endmodule

DAY_005/RCA_tb.v
module RCA_tb;
reg [3:0]a,b;
reg cin;
wire [3:0]sum;
wire carry;
integer i;

ripple_carry_adder dut(a,b,cin,sum,carry);

initial begin
 $monitor("a = %0d , b = %0d , cin = %0d ,sum = %0d ,carry = %0d",a,b,cin,sum,carry);
 $dumpfile("RCA.vcd");
 $dumpvars(0,RCA_tb);
end


initial begin
 for(i = 0 ; i <= 15 ; i = i+1)
  begin
     a = $urandom_range(15);
     b = $urandom_range(15);
     cin = 0;
     #10;
  end 

end
endmodule

DAY_005/RCA.vcd
$date
	Mon Jul  7 12:54:24 2025
$end
$version
	Icarus Verilog
$end
$timescale
	1s
$end
$scope module RCA_tb $end
$var wire 4 ! sum [3:0] $end
$var wire 1 " carry $end
$var reg 4 # a [3:0] $end
$var reg 4 $ b [3:0] $end
$var reg 1 % cin $end
$var integer 32 & i [31:0] $end
$scope module dut $end
$var wire 4 ' a [3:0] $end
$var wire 4 ( b [3:0] $end
$var wire 1 % cin $end
$var wire 4 ) sum [3:0] $end
$var wire 4 * cout [3:0] $end
$var wire 1 " carry $end
$scope module g1 $end
$var wire 1 % cin $end
$var wire 1 + in1 $end
$var wire 1 , in2 $end
$var wire 1 - s $end
$var wire 1 . c $end
$upscope $end
$scope module g2 $end
$var wire 1 / cin $end
$var wire 1 0 in1 $end
$var wire 1 1 in2 $end
$var wire 1 2 s $end
$var wire 1 3 c $end
$upscope $end
$scope module g3 $end
$var wire 1 4 cin $end
$var wire 1 5 in1 $end
$var wire 1 6 in2 $end
$var wire 1 7 s $end
$var wire 1 8 c $end
$upscope $end
$scope module g4 $end
$var wire 1 9 cin $end
$var wire 1 : in1 $end
$var wire 1 ; in2 $end
$var wire 1 < s $end
$var wire 1 = c $end
$upscope $end
$upscope $end
$upscope $end
$enddefinitions $end
$comment Show the parameter values. $end
$dumpall
$end
#0
$dumpvars
0=
1<
0;
1:
09
08
17
16
05
04
03
02
01
00
0/
0.
1-
0,
1+
b0 *
b1101 )
b100 (
b1001 '
b0 &
0%
b100 $
b1001 #
0"
b1101 !
$end
#10
12
07
b11 !
b11 )
0<
1,
11
06
0+
0:
b11 $
b11 (
b0 #
b0 '
b1 &
#20
1"
0-
02
b100 !
b100 )
17
b1000 *
1=
0,
01
16
1;
1:
b1100 $
b1100 (
b1000 #
b1000 '
b10 &
#30
0"
07
1-
b11 !
b11 )
12
b0 *
0=
06
0;
1+
10
0:
b0 $
b0 (
b11 #
b11 '
b11 &
#40
1"
b1000 *
1=
0-
b0 !
b0 )
02
1;
0+
00
1:
b1000 $
b1000 (
b1000 #
b1000 '
b100 &
#50
17
14
13
1/
b1011 *
1.
b100 !
b100 )
02
1,
1+
10
b1001 $
b1001 (
b1011 #
b1011 '
b101 &
#60
07
04
12
03
1<
0/
19
b1011 !
b1011 )
1-
0.
b1100 *
18
0,
16
15
b1100 $
b1100 (
b1111 #
b1111 '
b110 &
#70
17
14
02
b1110 *
13
b101 !
b101 )
0<
11
0;
b110 $
b110 (
b111 &
#80
07
04
0"
12
03
b1011 !
b1011 )
1<
b100 *
0=
1,
01
0+
0:
b101 $
b101 (
b110 #
b110 '
b1000 &
#90
14
19
1/
1"
12
13
07
18
0-
1.
b10 !
b10 )
0<
b1111 *
1=
11
06
1+
1:
b11 $
b11 (
b1111 #
b1111 '
b1001 &
#100
0"
1<
0=
09
17
08
b1100 !
b1100 )
02
04
0/
03
b0 *
0.
0,
01
16
1;
0+
00
05
0:
b1100 $
b1100 (
b0 #
b0 '
b1010 &
#110
1"
0<
1=
14
19
13
1-
b101 !
b101 )
17
b1110 *
18
11
0;
1+
10
15
1:
b110 $
b110 (
b1111 #
b1111 '
b1011 &
#120
0"
b1101 !
b1101 )
1<
b110 *
0=
0:
b111 #
b111 '
b1100 &
#130
09
08
04
0"
12
03
17
b1111 !
b1111 )
1<
b0 *
0=
1,
01
0+
05
1:
b101 $
b101 (
b1010 #
b1010 '
b1101 &
#140
14
02
13
1/
17
0-
b11 *
1.
b100 !
b100 )
0<
11
06
1+
00
0:
b11 $
b11 (
b1 #
b1 '
b1110 &
#150
07
04
12
03
0/
1-
b0 *
0.
b1011 !
b1011 )
1<
0,
01
1;
10
b1000 $
b1000 (
b11 #
b11 '
b1111 &
#160
b10000 &
