DAY_018/dff_pos_edge.v
module dff_sync_reset(input d , clk ,reset, output reg q);

always @(posedge clk)
 begin
  if(reset)
    q <= 1'b0;
  else
    q <= d;
 end
endmodule

DAY_018/dff_tb.v
module tb();
reg d, clk = 0, reset;
wire q;

dff_sync_reset dut(.d(d), .clk(clk), .reset(reset), .q(q));

// Clock generator
always #5 clk = ~clk;

integer i;

initial begin
  // Initialize signals
  d = 0;
  reset = 1;

  // Apply reset for 4 clock cycles
  repeat(4) @(posedge clk);
  reset = 0;

  // Stimulate data input
  for(i = 0; i < 10; i = i + 1) begin
    d = $urandom_range(0,1);
    @(posedge clk);
  end

  #10 $finish;
end

initial begin
  $monitor("Time = %0t | d = %b | clk = %b | reset = %b | q = %b", $time, d, clk, reset, q);
  $dumpfile("dff.vcd");
  $dumpvars(0, tb);
end

endmodule

DAY_018/dff.vcd
$date
	Mon Jul 28 10:59:59 2025
$end
$version
	Icarus Verilog
$end
$timescale
	1s
$end
$scope module tb $end
$var wire 1 ! q $end
$var reg 1 " clk $end
$var reg 1 # d $end
$var reg 1 $ reset $end
$var integer 32 % i [31:0] $end
$scope module dut $end
$var wire 1 " clk $end
$var wire 1 # d $end
$var wire 1 $ reset $end
$var reg 1 ! q $end
$upscope $end
$upscope $end
$enddefinitions $end
$comment Show the parameter values. $end
$dumpall
$end
#0
$dumpvars
bx %
1$
0#
0"
x!
$end
#5
0!
1"
#10
0"
#15
1"
#20
0"
#25
1"
#30
0"
#35
1#
b0 %
0$
1"
#40
0"
#45
0#
b1 %
1"
#50
0"
#55
b10 %
1"
#60
0"
#65
b11 %
1"
#70
0"
#75
1#
b100 %
1"
#80
0"
#85
1!
b101 %
1"
#90
0"
#95
0#
b110 %
1"
#100
0"
#105
0!
b111 %
1"
#110
0"
#115
1#
b1000 %
1"
#120
0"
#125
1!
b1001 %
1"
#130
0"
#135
b1010 %
1"
