DAY_019/dff_async_reset_sync_reset.v
module dff_async_reset_sync_reset(
    input  in,
    input  clk,
    input  async_reset,
    input  sync_reset,
    output reg q
);
    always @(posedge clk or posedge async_reset) begin
        if (async_reset)
            q <= 1'b0;
        else if (sync_reset)
            q <= 1'b0;
        else
            q <= in;
    end
endmodule

DAY_019/dff_async_reset_sync_reset_tb.v
/*module tb();
reg in ,clk,async_reset,sync_reset;
wire q;

dff_async_reset_sync_reset dut(in , clk ,async_reset,sync_reset,q);

always #5 clk = ~clk;

always #100 async_reset = ~async_reset;


integer i;

initial begin
 clk = 0;
 async_reset = 0;
 sync_reset = 0;

 for(i = 0 ; i < 10 i = i+1)
  begin
	  in = $urandom_range(0,1);
          #12;

	  if(i == 8)
	    sync_reset = 1;
          else 
	     sync_reset = 0;
  end

end

initial begin
 $monitor("Time = %0d , in = %0d , clk = %0d , async_reset = %0d , sync_reset = %0d , q = %0d ", $time,in,clk,async_reset,sync_reset,q);
 $dumpfile("dff_async_reset_sync_reset.vcd");
 $dumpvars(0,tb);
end
endmodule

*/

module tb();
    reg in, clk, async_reset, sync_reset;
    wire q;

    // Instantiate the DUT (Device Under Test)
    dff_async_reset_sync_reset dut(
        .in(in),
        .clk(clk),
        .async_reset(async_reset),
        .sync_reset(sync_reset),
        .q(q)
    );

    // Clock generation: 10 time units period
    always #5 clk = ~clk;

    // Toggle asynchronous reset every 100 time units
    always #200 async_reset = ~async_reset;

   always #23 in = ~in;

   always #113 sync_reset = ~sync_reset;

    initial begin
        clk = 0;
        async_reset = 1;
        sync_reset = 0;
        in = 1;

        #1000 $finish; // End the simulation after the loop
    end

    // Monitor changes and create VCD file
    initial begin
        $monitor("Time = %0t | in = %0b | clk = %0b | async_reset = %0b | sync_reset = %0b | q = %0b",
                  $time, in, clk, async_reset, sync_reset, q);
        $dumpfile("dff_async_reset_sync_reset.vcd");
        $dumpvars(0, tb);
    end
endmodule

DAY_019/dff_async_reset_sync_reset.vcd
$date
	Tue Jul 22 08:26:20 2025
$end
$version
	Icarus Verilog
$end
$timescale
	1s
$end
$scope module tb $end
$var wire 1 ! q $end
$var reg 1 " async_reset $end
$var reg 1 # clk $end
$var reg 1 $ in $end
$var reg 1 % sync_reset $end
$scope module dut $end
$var wire 1 " async_reset $end
$var wire 1 # clk $end
$var wire 1 $ in $end
$var wire 1 % sync_reset $end
$var reg 1 ! q $end
$upscope $end
$upscope $end
$enddefinitions $end
$comment Show the parameter values. $end
$dumpall
$end
#0
$dumpvars
0%
1$
0#
1"
0!
$end
#5
1#
#10
0#
#15
1#
#20
0#
#23
0$
#25
1#
#30
0#
#35
1#
#40
0#
#45
1#
#46
1$
#50
0#
#55
1#
#60
0#
#65
1#
#69
0$
#70
0#
#75
1#
#80
0#
#85
1#
#90
0#
#92
1$
#95
1#
#100
0#
#105
1#
#110
0#
#113
1%
#115
1#
0$
#120
0#
#125
1#
#130
0#
#135
1#
#138
1$
#140
0#
#145
1#
#150
0#
#155
1#
#160
0#
#161
0$
#165
1#
#170
0#
#175
1#
#180
0#
#184
1$
#185
1#
#190
0#
#195
1#
#200
0#
0"
#205
1#
#207
0$
#210
0#
#215
1#
#220
0#
#225
1#
#226
0%
#230
0#
1$
#235
1!
1#
#240
0#
#245
1#
#250
0#
#253
0$
#255
0!
1#
#260
0#
#265
1#
#270
0#
#275
1#
#276
1$
#280
0#
#285
1!
1#
#290
0#
#295
1#
#299
0$
#300
0#
#305
0!
1#
#310
0#
#315
1#
#320
0#
#322
1$
#325
1!
1#
#330
0#
#335
1#
#339
1%
#340
0#
#345
0!
1#
0$
#350
0#
#355
1#
#360
0#
#365
1#
#368
1$
#370
0#
#375
1#
#380
0#
#385
1#
#390
0#
#391
0$
#395
1#
#400
0#
1"
#405
1#
#410
0#
#414
1$
#415
1#
#420
0#
#425
1#
#430
0#
#435
1#
#437
0$
#440
0#
#445
1#
#450
0#
#452
0%
#455
1#
#460
0#
1$
#465
1#
#470
0#
#475
1#
#480
0#
#483
0$
#485
1#
#490
0#
#495
1#
#500
0#
#505
1#
#506
1$
#510
0#
#515
1#
#520
0#
#525
1#
#529
0$
#530
0#
#535
1#
#540
0#
#545
1#
#550
0#
#552
1$
#555
1#
#560
0#
#565
1#
1%
#570
0#
#575
1#
0$
#580
0#
#585
1#
#590
0#
#595
1#
#598
1$
#600
0#
0"
#605
1#
#610
0#
#615
1#
#620
0#
#621
0$
#625
1#
#630
0#
#635
1#
#640
0#
#644
1$
#645
1#
#650
0#
#655
1#
#660
0#
#665
1#
#667
0$
#670
0#
#675
1#
#678
0%
#680
0#
#685
1#
#690
0#
1$
#695
1!
1#
#700
0#
#705
1#
#710
0#
#713
0$
#715
0!
1#
#720
0#
#725
1#
#730
0#
#735
1#
#736
1$
#740
0#
#745
1!
1#
#750
0#
#755
1#
#759
0$
#760
0#
#765
0!
1#
#770
0#
#775
1#
#780
0#
#782
1$
#785
1!
1#
#790
0#
#791
1%
#795
0!
1#
#800
0#
1"
#805
1#
0$
#810
0#
#815
1#
#820
0#
#825
1#
#828
1$
#830
0#
#835
1#
#840
0#
#845
1#
#850
0#
#851
0$
#855
1#
#860
0#
#865
1#
#870
0#
#874
1$
#875
1#
#880
0#
#885
1#
#890
0#
#895
1#
#897
0$
#900
0#
#904
0%
#905
1#
#910
0#
#915
1#
#920
0#
1$
#925
1#
#930
0#
#935
1#
#940
0#
#943
0$
#945
1#
#950
0#
#955
1#
#960
0#
#965
1#
#966
1$
#970
0#
#975
1#
#980
0#
#985
1#
#989
0$
#990
0#
#995
1#
#1000
0#
0"
