DAY_012/priority_encoder_4x2.v
module encoder(
  input [3:0] in,
  input en,
  output reg [1:0] y
);

  always @(*) begin
    if (en) begin
      casex (in)
        4'b1xxx: y = 2'b11;
  	4'b01xx: y = 2'b10;
  	4'b001x: y = 2'b01;
  	4'b0001: y = 2'b00;
  	default: y = 2'b00;  // Optional: fallback for invalid/multiple-bit input
      endcase
    end else begin
      y = 2'b00; // Output 0 when disabled
    end
  end

endmodule

DAY_012/tb.v
module tb();
reg [3:0]in;
reg en;
wire [1:0]y;

encoder dut(in,en,y);

integer i;
initial begin
  en =0;
  #10;
  for(i = 0 ; i < 15 ; i = i + 1)
    begin
	    en =1;
    	    in = i;
        #10;
    end
end

initial begin
 $monitor("Time = %0t , in = %0d , en = %0d , y= %0d ",$time,in,en,y);
 $dumpfile("encoder.vcd");
 $dumpvars(0,tb);
end

endmodule

DAY_012/encoder.vcd
$date
	Tue Jul 15 21:48:45 2025
$end
$version
	Icarus Verilog
$end
$timescale
	1s
$end
$scope module tb $end
$var wire 2 ! y [1:0] $end
$var reg 1 " en $end
$var reg 4 # in [3:0] $end
$var integer 32 $ i [31:0] $end
$scope module dut $end
$var wire 1 " en $end
$var wire 4 % in [3:0] $end
$var reg 2 & y [1:0] $end
$upscope $end
$upscope $end
$enddefinitions $end
$comment Show the parameter values. $end
$dumpall
$end
#0
$dumpvars
b0 &
bx %
bx $
bx #
0"
b0 !
$end
#10
b0 #
b0 %
1"
b0 $
#20
b1 #
b1 %
b1 $
#30
b1 !
b1 &
b10 #
b10 %
b10 $
#40
b11 #
b11 %
b11 $
#50
b10 !
b10 &
b100 #
b100 %
b100 $
#60
b101 #
b101 %
b101 $
#70
b110 #
b110 %
b110 $
#80
b111 #
b111 %
b111 $
#90
b11 !
b11 &
b1000 #
b1000 %
b1000 $
#100
b1001 #
b1001 %
b1001 $
#110
b1010 #
b1010 %
b1010 $
#120
b1011 #
b1011 %
b1011 $
#130
b1100 #
b1100 %
b1100 $
#140
b1101 #
b1101 %
b1101 $
#150
b1110 #
b1110 %
b1110 $
#160
b1111 $
