DAY_002/mux2x1_using_gates/mux2x1.v
module mux2x1(input in1 ,in2 , sel , output out);
wire w1,w2,w3;
not g1(w1,sel);
and g2(w2,in1,w1);
and g3(w3,in2,sel);
or g4(out,w2,w3);
endmodule

DAY_002/mux2x1_using_gates/mux2x1_TB.v
module mux_tb;
reg in1,in2,sel;
wire out;

mux2x1 dut(in1,in2,sel,out);

initial begin
  in1 = 0 ; in2 = 0 ; sel = 0;#10;
  in1 = 0 ; in2 = 0 ; sel = 1;#10;
  in1 = 0 ; in2 = 1 ; sel = 1;#10;
  in1 = 0 ; in2 = 1 ; sel = 0;#10;
  in1 = 1 ; in2 = 0 ; sel = 0;#10;
  in1 = 1 ; in2 = 0 ; sel = 1;#10;
  in1 = 1 ; in2 = 1 ; sel = 0;#10;
  in1 = 1 ; in2 = 1 ; sel = 1;#10;
end

initial begin
   $monitor("in1 = %0d , in2 = %0d , sel = %0d, out = %0d " , in1,in2,sel,out);
end


initial begin
 $dumpfile("mux2x1.vcd");
 $dumpvars(0,mux_tb);
end
endmodule

DAY_002/mux2x1_using_gates/mux2x1.vcd
$date
	Thu Jul  3 22:24:43 2025
$end
$version
	Icarus Verilog
$end
$timescale
	1s
$end
$scope module mux_tb $end
$var wire 1 ! out $end
$var reg 1 " in1 $end
$var reg 1 # in2 $end
$var reg 1 $ sel $end
$scope module dut $end
$var wire 1 " in1 $end
$var wire 1 # in2 $end
$var wire 1 ! out $end
$var wire 1 $ sel $end
$var wire 1 % w1 $end
$var wire 1 & w2 $end
$var wire 1 ' w3 $end
$upscope $end
$upscope $end
$enddefinitions $end
$comment Show the parameter values. $end
$dumpall
$end
#0
$dumpvars
0'
0&
1%
0$
0#
0"
0!
$end
#10
0%
1$
#20
1!
1'
1#
#30
0!
1%
0'
0$
#40
1!
1&
0#
1"
#50
0!
0&
0%
1$
#60
1!
1&
1%
0$
1#
#70
0&
0%
1'
1$
