DAY_015/g2b_converter.v
module g2b_converter(gray,binary);
input [3:0]gray;
output [3:0]binary;

assign binary[3] = gray[3];  		 // MSB is the same
assign binary[2] = gray[2] ^ binary[3];  // B2 = G2 ^ B3
assign binary[1] = gray[1] ^ binary[2];  // B1 = G1 ^ B2
assign binary[0] = gray[0] ^ binary[1];  // B0 = G0 ^ B1
endmodule

DAY_015/g2b_tb.v
module tb();

wire [3:0] binary;
reg [3:0] gray;

g2b_converter dut(gray,binary);


integer i;
initial begin
 for(i=0 ; i<15 ; i=i+1)
  begin
    gray = i;
    #10;
  end
end

initial begin
 $monitor("Time = %0t , binary = %0d , gray = %0d ",$time,binary,gray);
 $dumpfile("g2b.vcd");
 $dumpvars(0,tb);
end
endmodule

DAY_015/g2b.vcd
$date
	Sat Jul 19 10:07:40 2025
$end
$version
	Icarus Verilog
$end
$timescale
	1s
$end
$scope module tb $end
$var wire 4 ! binary [3:0] $end
$var reg 4 " gray [3:0] $end
$var integer 32 # i [31:0] $end
$scope module dut $end
$var wire 4 $ gray [3:0] $end
$var wire 4 % binary [3:0] $end
$upscope $end
$upscope $end
$enddefinitions $end
$comment Show the parameter values. $end
$dumpall
$end
#0
$dumpvars
b0 %
b0 $
b0 #
b0 "
b0 !
$end
#10
b1 !
b1 %
b1 "
b1 $
b1 #
#20
b11 !
b11 %
b10 "
b10 $
b10 #
#30
b10 !
b10 %
b11 "
b11 $
b11 #
#40
b111 !
b111 %
b100 "
b100 $
b100 #
#50
b110 !
b110 %
b101 "
b101 $
b101 #
#60
b100 !
b100 %
b110 "
b110 $
b110 #
#70
b101 !
b101 %
b111 "
b111 $
b111 #
#80
b1111 !
b1111 %
b1000 "
b1000 $
b1000 #
#90
b1110 !
b1110 %
b1001 "
b1001 $
b1001 #
#100
b1100 !
b1100 %
b1010 "
b1010 $
b1010 #
#110
b1101 !
b1101 %
b1011 "
b1011 $
b1011 #
#120
b1000 !
b1000 %
b1100 "
b1100 $
b1100 #
#130
b1001 !
b1001 %
b1101 "
b1101 $
b1101 #
#140
b1011 !
b1011 %
b1110 "
b1110 $
b1110 #
#150
b1111 #
