DAY_009/decoder2x4.v
module decoder2x4(input a , b , output [3:0] F);
assign F[0] = (~a & ~b);
assign F[1] = (~a & b);
assign F[2] = (a & ~b);
assign F[3] = (a & b);
endmodule

DAY_009/decoder2x4_tb.v
module decoder_tb();
reg a,b;
wire [3:0]F;

decoder2x4 uut(a,b,F);
integer i;

initial begin
 for(i = 0 ; i <=10 ; i=i+1) 
    begin
	#10;
    	{a,b} = $urandom_range(0,4);
    end  
end



initial begin
  $monitor("a = %0d , b = %0d , F = %0d",a,b,F);
  $dumpfile("decoder.vcd");
  $dumpvars(0,decoder_tb);
end
endmodule

DAY_009/decoder.vcd
$date
	Tue Jul  8 10:26:34 2025
$end
$version
	Icarus Verilog
$end
$timescale
	1s
$end
$scope module decoder_tb $end
$var wire 4 ! F [3:0] $end
$var reg 1 " a $end
$var reg 1 # b $end
$var integer 32 $ i [31:0] $end
$scope module uut $end
$var wire 1 " a $end
$var wire 1 # b $end
$var wire 4 % F [3:0] $end
$upscope $end
$upscope $end
$enddefinitions $end
$comment Show the parameter values. $end
$dumpall
$end
#0
$dumpvars
bx %
b0 $
x#
x"
bx !
$end
#10
b100 !
b100 %
b1 $
1"
0#
#20
b10 !
b10 %
b10 $
0"
1#
#30
b1 !
b1 %
b11 $
0#
#40
b100 $
#50
b100 !
b100 %
b101 $
1"
#60
b1000 !
b1000 %
b110 $
1#
#70
b1 !
b1 %
b111 $
0"
0#
#80
b1000 $
#90
b100 !
b100 %
b1001 $
1"
#100
b1010 $
#110
b1000 !
b1000 %
b1011 $
1#
