DAY_013/decimal_bcd.v
module bcd(in,en,y);
input [9:0]in;
input en;
output reg [3:0]y;

always @(*)
 begin
  if(en)
    begin
      case(in)
        10'b0000000001 : y = 4'd0;
	10'b0000000010 : y = 4'd1;
	10'b0000000100 : y = 4'd2;
	10'b0000001000 : y = 4'd3;
	10'b0000010000 : y = 4'd4;
	10'b0000100000 : y = 4'd5;
	10'b0001000000 : y = 4'd6;
	10'b0010000000 : y = 4'd7;
	10'b0100000000 : y = 4'd8;
	10'b1000000000 : y = 4'd9;
	default : y = 4'b0000;
      endcase
     end
  else
	y = 4'b0000;
 end

endmodule


/*

module bcd(in,en,y);
input [9:0]in;
input en;
output reg [3:0]y;

always @(*)
 begin
  if(en)
   begin
    if (in[0]) y = 4'd0;
    else if (in[1]) y = 4'd1;
    else if (in[2]) y = 4'd2;
    else if (in[3]) y = 4'd3;
    else if (in[4]) y = 4'd4;
    else if (in[5]) y = 4'd5;
    else if (in[6]) y = 4'd6;
    else if (in[7]) y = 4'd7;
    else if (in[8]) y = 4'd8;
    else if (in[9]) y = 4'd9;
    else y =4'd0;
  end 
else
	y = 4'b0000;
 end

endmodule



//casex

module bcd(in,en,y);
input [9:0]in;
input en;
output reg [3:0]y;

always @(*)
 begin
  if(en)
    begin
      casex(in)
        10'b1xxxxxxxxx : y = 4'd9;
	10'b01xxxxxxxx : y = 4'd8;
	10'b001xxxxxxx : y = 4'd7;
	10'b0001xxxxxx : y = 4'd6;
	10'b00001xxxxx : y = 4'd5;
	10'b000001xxxx : y = 4'd4;
	10'b0000001xxx : y = 4'd3;
	10'b00000001xx : y = 4'd2;
	10'b000000001x : y = 4'd1;
	10'b0000000001 : y = 4'd0;
	default : y = 4'b0000;
      endcase
     end
  else
	y = 4'b0000;
 end

endmodule*/

DAY_013/decimal_bcd_tb.v
module tb();
reg [9:0] in;
reg en;
wire [3:0]y;

bcd dut(in,en,y);

integer i;

initial begin
 for(i = 0 ;i < 10 ;i = i + 1)
  begin
    en = 1'b1;
    in[i]= 1'b1;
    #10;
    in = 10'b0;
  end
 $finish;
end

initial begin
 $monitor("Time = %0t , in = %0d , en = %0d , y = %0d",$time,in,en,y);
 $dumpfile("decimal_bcd.vcd");
 $dumpvars(0,tb);
end
endmodule

DAY_013/decimal_bcd.vcd
$date
	Wed Jul 16 17:07:52 2025
$end
$version
	Icarus Verilog
$end
$timescale
	1s
$end
$scope module tb $end
$var wire 4 ! y [3:0] $end
$var reg 1 " en $end
$var reg 10 # in [9:0] $end
$var integer 32 $ i [31:0] $end
$scope module dut $end
$var wire 1 " en $end
$var wire 10 % in [9:0] $end
$var reg 4 & y [3:0] $end
$upscope $end
$upscope $end
$enddefinitions $end
$comment Show the parameter values. $end
$dumpall
$end
#0
$dumpvars
b0 &
bx1 %
b0 $
bx1 #
1"
b0 !
$end
#10
b1 !
b1 &
b1 $
b10 #
b10 %
#20
b10 !
b10 &
b10 $
b100 #
b100 %
#30
b11 !
b11 &
b11 $
b1000 #
b1000 %
#40
b100 !
b100 &
b100 $
b10000 #
b10000 %
#50
b101 !
b101 &
b101 $
b100000 #
b100000 %
#60
b110 !
b110 &
b110 $
b1000000 #
b1000000 %
#70
b111 !
b111 &
b111 $
b10000000 #
b10000000 %
#80
b1000 !
b1000 &
b1000 $
b100000000 #
b100000000 %
#90
b1001 !
b1001 &
b1001 $
b1000000000 #
b1000000000 %
#100
b0 !
b0 &
b1010 $
b0 #
b0 %
